{"name":"ravitavilyservername:extract","display_name":"ravitavilyservername:extract","description":"Extract and process content from a list of URLs using Tavily API. Can handle up to 20 URLs at once.","permission":"read_only","input_schema":{"type":"object","properties":{"urls":{"type":"array","title":null,"description":"list of URLs to extract content from (max 20)","properties":null,"required":null,"items":{"type":"string","title":null,"description":null,"properties":null,"required":null,"items":null,"default":null,"enum":null,"minimum":null,"maximum":null,"minLength":null,"maxLength":null,"pattern":null,"format":null,"in_field":null,"aliasName":null,"anyOf":null,"oneOf":null,"allOf":null},"default":null,"enum":null,"minimum":null,"maximum":null,"minLength":null,"maxLength":null,"pattern":null,"format":null,"in_field":null,"aliasName":null,"anyOf":null,"oneOf":null,"allOf":null},"options":{"type":"object","title":null,"description":"Extraction options","properties":{"extractDepth":{"type":"string","title":null,"description":"Extraction depth","properties":null,"required":null,"items":null,"default":null,"enum":["basic","advanced"],"minimum":null,"maximum":null,"minLength":null,"maxLength":null,"pattern":null,"format":null,"in_field":null,"aliasName":null,"anyOf":null,"oneOf":null,"allOf":null},"includeImages":{"type":"boolean","title":null,"description":"Include images in results","properties":null,"required":null,"items":null,"default":null,"enum":null,"minimum":null,"maximum":null,"minLength":null,"maxLength":null,"pattern":null,"format":null,"in_field":null,"aliasName":null,"anyOf":null,"oneOf":null,"allOf":null}},"required":null,"items":null,"default":null,"enum":null,"minimum":null,"maximum":null,"minLength":null,"maxLength":null,"pattern":null,"format":null,"in_field":null,"aliasName":null,"anyOf":null,"oneOf":null,"allOf":null}},"required":["urls"]},"output_schema":{"type":"object","description":null,"properties":null,"items":null,"required":[],"format":null,"anyOf":null,"oneOf":null,"allOf":null},"binding":{"openapi":null,"python":null,"wxflows":null,"skill":null,"client_side":null,"conversational_search":null,"mcp":{"server_url":null,"source":"public-registry","env":null,"command":"npx","args":["-y","@mcptools/mcp-tavily"],"transport":null,"connections":{"name":"0fc307e1-f5c4-410a-825c-006cb0e7c267"}},"flow":null,"langflow":null},"tags":null,"is_async":false,"restrictions":"editable","bundled_agent_id":null}